ansible/module_utils/pm2.py
ansible/modules/pm2/__init__.py
ansible/modules/pm2/pm2.py
ansible_modules_pm2-0.1.0.dist-info/LICENSE
ansible_modules_pm2-0.1.0.dist-info/METADATA
ansible_modules_pm2-0.1.0.dist-info/WHEEL
ansible_modules_pm2-0.1.0.dist-info/top_level.txt
ansible_modules_pm2-0.1.0.dist-info/RECORD
