Metadata-Version: 2.1
Name: ansible-modules-pm2
Version: 0.1.0
Summary: Ansible module to manage processes via PM2
Home-page: https://github.com/10sr/ansible-modules-pm2
Author: 10sr
Author-email: 8.slashes@gmail.com
License: GNU GPL v3
Keywords: ansible
Platform: UNKNOWN
Classifier: License :: OSI Approved :: GNU General Public License v3 or later (GPLv3+)
Classifier: Programming Language :: Python :: 3
Requires-Dist: ansible (>=2.2.0)
Provides-Extra: dev
Requires-Dist: molecule[docker] ; extra == 'dev'
Requires-Dist: pyyaml ; extra == 'dev'
Requires-Dist: jinja2 ; extra == 'dev'
Requires-Dist: tabulate ; extra == 'dev'
Requires-Dist: black ; extra == 'dev'
Requires-Dist: isort ; extra == 'dev'
Requires-Dist: flake8 ; extra == 'dev'
Requires-Dist: flake8-black ; extra == 'dev'
Requires-Dist: flake8-isort ; extra == 'dev'
Requires-Dist: pep8-naming ; extra == 'dev'
